overflow/__init__.py
overflow/__main__.py
overflow/cli.py
overflow/basins/__init__.py
overflow/basins/core/__init__.py
overflow/basins/core/basin_polygons.py
overflow/basins/core/basins.py
overflow/basins/tiled/__init__.py
overflow/basins/tiled/basins_tiled.py
overflow/basins/tiled/global_state.py
overflow/breach_paths_least_cost/__init__.py
overflow/breach_paths_least_cost/breach_paths_least_cost.py
overflow/breach_paths_least_cost/breach_paths_least_cost_cuda.py
overflow/breach_single_cell_pits/__init__.py
overflow/breach_single_cell_pits/breach_single_cell_pits.py
overflow/extract_streams/__init__.py
overflow/extract_streams/core/__init__.py
overflow/extract_streams/core/extract_streams.py
overflow/extract_streams/tiled/__init__.py
overflow/extract_streams/tiled/extract_streams_tiled.py
overflow/fill_depressions/__init__.py
overflow/fill_depressions/core/__init__.py
overflow/fill_depressions/core/fill_depressions.py
overflow/fill_depressions/core/watershed_graph.py
overflow/fill_depressions/tiled/__init__.py
overflow/fill_depressions/tiled/fill_depressions_tiled.py
overflow/fill_depressions/tiled/global_state.py
overflow/fix_flats/__init__.py
overflow/fix_flats/core/__init__.py
overflow/fix_flats/core/fix_flats.py
overflow/fix_flats/tiled/__init__.py
overflow/fix_flats/tiled/fix_flats_tiled.py
overflow/fix_flats/tiled/flat_distance.py
overflow/fix_flats/tiled/flat_mask.py
overflow/fix_flats/tiled/global_state.py
overflow/fix_flats/tiled/graphs.py
overflow/fix_flats/tiled/resolve_flats.py
overflow/fix_flats/tiled/update_fdr.py
overflow/flow_accumulation/__init__.py
overflow/flow_accumulation/core/__init__.py
overflow/flow_accumulation/core/flow_accumulation.py
overflow/flow_accumulation/tiled/__init__.py
overflow/flow_accumulation/tiled/flow_accumulation_tiled.py
overflow/flow_accumulation/tiled/global_state.py
overflow/flow_direction/__init__.py
overflow/flow_direction/flow_direction.py
overflow/util/constants.py
overflow/util/numba_types.py
overflow_hydro-0.1.4.dist-info/licenses/LICENSE
overflow_hydro-0.1.4.dist-info/METADATA
overflow_hydro-0.1.4.dist-info/WHEEL
overflow_hydro-0.1.4.dist-info/entry_points.txt
overflow_hydro-0.1.4.dist-info/top_level.txt
overflow_hydro-0.1.4.dist-info/RECORD
