Metadata-Version: 2.4
Name: overflow-hydro
Version: 0.1.4
Summary: High-performance Python library for hydrological terrain analysis with parallel, tiled algorithms
Author: Overflow Contributors
License: MIT
Project-URL: Homepage, https://github.com/fema-ffrd/overflow
Project-URL: Documentation, https://github.com/fema-ffrd/overflow#readme
Project-URL: Repository, https://github.com/fema-ffrd/overflow
Project-URL: Issues, https://github.com/fema-ffrd/overflow/issues
Keywords: hydrology,terrain-analysis,dem,digital-elevation-model,flow-accumulation,watershed,geospatial,gis,parallel-processing,numba
Classifier: Development Status :: 3 - Alpha
Classifier: Intended Audience :: Science/Research
Classifier: Topic :: Scientific/Engineering :: GIS
Classifier: Topic :: Scientific/Engineering :: Hydrology
Classifier: License :: OSI Approved :: MIT License
Classifier: Programming Language :: Python :: 3
Classifier: Programming Language :: Python :: 3.11
Classifier: Programming Language :: Python :: 3.12
Classifier: Operating System :: OS Independent
Requires-Python: >=3.11
License-File: LICENSE
Requires-Dist: numpy>=1.26.0
Requires-Dist: numba>=0.59.0
Requires-Dist: click>=8.0.0
Requires-Dist: rich>=13.0.0
Requires-Dist: shapely>=2.0.0
Requires-Dist: psutil>=6.0.0
Requires-Dist: tqdm>=4.62.0
Provides-Extra: cuda
Provides-Extra: dev
Requires-Dist: pytest>=8.0.0; extra == "dev"
Requires-Dist: black>=24.0.0; extra == "dev"
Requires-Dist: pylint>=3.1.0; extra == "dev"
Dynamic: license-file
